{
  "gitSyncId": "68e110fdb463bf1f5806174c_660daf6a-77a5-4fa8-942a-25004c064a72",
  "id": "Player Characters_deleteCharacter",
  "pluginId": "postgres-plugin",
  "pluginType": "DB",
  "unpublishedAction": {
    "actionConfiguration": {
      "body": "DELETE FROM characters \nWHERE id = {{this.params.characterId}} \nAND player_email = {{appsmith.store.user_email}};",
      "encodeParamsToggle": true,
      "paginationType": "NONE",
      "pluginSpecifiedTemplates": [
        {
          "value": true
        }
      ],
      "timeoutInMillisecond": 10000
    },
    "confirmBeforeExecute": false,
    "datasource": {
      "id": "Genesys",
      "isAutoGenerated": false,
      "name": "Genesys",
      "pluginId": "postgres-plugin"
    },
    "dynamicBindingPathList": [
      {
        "key": "body"
      }
    ],
    "name": "deleteCharacter",
    "pageId": "Player Characters",
    "runBehaviour": "MANUAL",
    "userSetOnLoad": false
  }
}